[{"int_division_key":"1","old_key":"BRSL","tx_division_name":"BARISAL","dtt_mod":"0000-00-00 00:00:00","is_active":"1","int_mod_user_key":"0"},{"int_division_key":"2","old_key":"CHTG","tx_division_name":"CHITTAGONG","dtt_mod":"0000-00-00 00:00:00","is_active":"1","int_mod_user_key":"0"},{"int_division_key":"3","old_key":"DHAK","tx_division_name":"DHAKA","dtt_mod":"0000-00-00 00:00:00","is_active":"1","int_mod_user_key":"0"},{"int_division_key":"4","old_key":"KHLN","tx_division_name":"KHULNA","dtt_mod":"0000-00-00 00:00:00","is_active":"1","int_mod_user_key":"0"},{"int_division_key":"5","old_key":"RAJH","tx_division_name":"RAJSHAHI","dtt_mod":"0000-00-00 00:00:00","is_active":"1","int_mod_user_key":"0"},{"int_division_key":"6","old_key":"RGPR","tx_division_name":"RANGPUR","dtt_mod":"0000-00-00 00:00:00","is_active":"1","int_mod_user_key":"0"},{"int_division_key":"7","old_key":"SYLT","tx_division_name":"SYLHET","dtt_mod":"0000-00-00 00:00:00","is_active":"1","int_mod_user_key":"0"}]